albhed/__init__.py
albhed-1.2.0.dist-info/licenses/LICENSE
albhed-1.2.0.dist-info/METADATA
albhed-1.2.0.dist-info/WHEEL
albhed-1.2.0.dist-info/entry_points.txt
albhed-1.2.0.dist-info/top_level.txt
albhed-1.2.0.dist-info/RECORD
