Metadata-Version: 2.4
Name: albhed
Version: 1.2.0
Summary: Converts English text to Albhed, a fictional language from the Final Fantasy series.
Requires-Python: >=3.13
License-File: LICENSE
Requires-Dist: typer>=0.16.1
Dynamic: license-file
